kometautils/__init__.py
kometautils/args.py
kometautils/exceptions.py
kometautils/logging.py
kometautils/schedule.py
kometautils/util.py
kometautils/yaml.py
kometautils-0.3.4.dist-info/LICENSE
kometautils-0.3.4.dist-info/METADATA
kometautils-0.3.4.dist-info/WHEEL
kometautils-0.3.4.dist-info/top_level.txt
kometautils-0.3.4.dist-info/RECORD
